count_word_package/__init__.py
count_word_package-0.0.1.dist-info/LICENSE
count_word_package-0.0.1.dist-info/METADATA
count_word_package-0.0.1.dist-info/WHEEL
count_word_package-0.0.1.dist-info/top_level.txt
count_word_package-0.0.1.dist-info/RECORD
