Metadata-Version: 2.1
Name: count-word-package
Version: 0.0.1
Summary: Word Count using Counter collections function package
Home-page: https://github.com/kenmwangi/count-word
Author: Ken mwangi
Author-email: contact@kenmwangi.com
License: MIT
Platform: UNKNOWN
Requires-Python: >=3.8
